ned/__init__.py
ned/helper.py
ned/metadata.py
ned/ned.py
tests/__init__.py
tests/test_ned.py
ned_py-0.31.dist-info/LICENSE
ned_py-0.31.dist-info/METADATA
ned_py-0.31.dist-info/WHEEL
ned_py-0.31.dist-info/top_level.txt
ned_py-0.31.dist-info/RECORD
